{
  "dateTimeFormat": "iso8601",
  "events": [
    {
      "start": "1994-11-07",
      "title": "GLINT 300SX",
      "description": ""
    },
    {
      "start": "1996-03-11",
      "title": "GLINT Delta",
      "description": ""
    },
    {
      "start": "1996-08-05",
      "title": "Permedia",
      "description": ""
    },
    {
      "start": "1996-08-05",
      "title": "GLINT 500TX",
      "description": ""
    },
    {
      "start": "1997-05-07",
      "title": "GLINT MX",
      "description": ""
    },
    {
      "start": "1997-05-21",
      "title": "Permedia 2",
      "description": ""
    },
    {
      "start": "1998-05-27",
      "title": "GLINT GMX",
      "description": ""
    },
    {
      "start": "1998-11-16",
      "title": "Oxygen RPM",
      "description": ""
    },
    {
      "start": "1999-05-01",
      "title": "Oxygen VX1",
      "description": "<a href=\"https://www.thefreelibrary.com/OXYGEN+VX1+WORKSTATION+GRAPHICS+ACCELERATOR+BOARD+DEBUTS.-a054428331\">Oxygen VX1 Workstation Graphics Board Debuts</a>"
    },
    {
      "start": "1999-07-01",
      "title": "Oxygen GVX1",
      "description": "<a href=\"https://www.thefreelibrary.com/OXYGEN+GVX1+DELIVERS+OUTSTANDING+BENCHMARK+PERFORMANCE.-a054935953\">Oxygen GVX1 delivers outstanding benchmark performance</a>"
    },
    {
      "start": "2000-04-01",
      "title": "Oxygen GVX210",
      "description": "<a href=\"https://www.thefreelibrary.com/3D+LABS+DEBUTS+OXYGEN+GVX210+WORKSTATION+GRAPHICS+ACCELERATOR.-a060477758\">3Dlabs debuts Oxygen GVX210 workstation graphics accelerator</a>"
    },
    {
      "start": "2000-09-01",
      "title": "Oxygen GVX420",
      "description": "and GVX1 Pro<br><a href=\"https://www.thefreelibrary.com/3DLABS+ADDS+TWO+OXYGEN+WORKSTATION+GRAPHICS+ACCELERATORS-a064393732\">3Dlabs adds two Oxygen Workstation graphics accelerators</a>"
    },
    {
      "start": "2001-07-16",
      "title": "Wildcat II 5000",
      "description": ""
    },
    {
      "start": "2002-12-01",
      "title": "Wildcat4 7210",
      "description": "<a href=\"https://www.thefreelibrary.com/3DLABS+INTRODUCES+NEW+HIGH-END+WILDCAT4+AGP+8X+GRAPHICS.-a094294095\">3Dlabs introduces new high-end Wildcat4 AGP 8x graphics</a>"
    }
  ]
}